truecallerpy/__init__.py
truecallerpy/cli.py
truecallerpy/login.py
truecallerpy/search.py
truecallerpy/verify_otp.py
truecallerpy/data/__init__.py
truecallerpy/data/phones_list.py
truecallerpy-1.0.3.dist-info/LICENSE
truecallerpy-1.0.3.dist-info/METADATA
truecallerpy-1.0.3.dist-info/WHEEL
truecallerpy-1.0.3.dist-info/entry_points.txt
truecallerpy-1.0.3.dist-info/top_level.txt
truecallerpy-1.0.3.dist-info/RECORD
