Metadata-Version: 2.1
Name: truecallerpy
Version: 1.0.3
Summary: TruecallerPy is a Python package that provides functionalities to interact with the Truecaller API. It allows you to perform login, OTP verification, and phone number search using Truecaller.
Author-email: Sumith Emmadi <sumithemmadi244@gmail.com>
Maintainer-email: Sumith Emmadi <sumithemmadi244@gmail.com>
License: MIT License
Project-URL: Homepage, https://github.com/sumithemmadi/truecallerpy
Project-URL: Documentation, https://github.com/sumithemmadi/truecallerpy
Project-URL: Repository, https://github.com/sumithemmadi/truecallerpy
Project-URL: Changelog, https://github.com/sumithemmadi/truecallerpy
Project-URL: Bug Tracker, https://github.com/sumithemmadi/truecallerpy/issues
Keywords: truecallerpy,truecaller,search,phone,number,phonenumber,information,mobile
Classifier: Topic :: Utilities
Classifier: Natural Language :: English
Classifier: Operating System :: OS Independent
Classifier: Programming Language :: Python :: 3
Classifier: License :: OSI Approved :: MIT License
License-File: LICENSE
